rqdb/__init__.py
rqdb/async_connection.py
rqdb/async_cursor.py
rqdb/connection.py
rqdb/cursor.py
rqdb/errors.py
rqdb/explain.py
rqdb/logging.py
rqdb/preprocessing.py
rqdb/py.typed
rqdb/result.py
rqdb/types.py
rqdb-1.6.4.dist-info/licenses/LICENSE
rqdb-1.6.4.dist-info/METADATA
rqdb-1.6.4.dist-info/WHEEL
rqdb-1.6.4.dist-info/top_level.txt
rqdb-1.6.4.dist-info/RECORD
