Metadata-Version: 2.4
Name: rqdb
Version: 1.6.4
Summary: An unofficial python client for RQLite
Home-page: https://github.com/tjstretchalot/rqdb
Author: Timothy Moore
Author-email: mtimothy984@gmail.com
Classifier: Programming Language :: Python :: 3
Classifier: Programming Language :: Python :: 3.9
Classifier: Programming Language :: Python :: 3.10
Classifier: Programming Language :: Python :: 3.11
Classifier: Programming Language :: Python :: 3.12
Classifier: Programming Language :: Python :: 3.13
Classifier: License :: OSI Approved :: MIT License
Classifier: Intended Audience :: Developers
License-File: LICENSE
Requires-Dist: requests
Requires-Dist: aiohttp
Dynamic: license-file
